zreion/__init__.py
zreion/_zreion.cp38-win32.pyd
zreion/zreion.py
zreion/zreion.pyx
zreion-0.2.2.dist-info/AUTHORS.rst
zreion-0.2.2.dist-info/LICENSE.txt
zreion-0.2.2.dist-info/METADATA
zreion-0.2.2.dist-info/WHEEL
zreion-0.2.2.dist-info/top_level.txt
zreion-0.2.2.dist-info/RECORD
