Metadata-Version: 2.1
Name: zreion
Version: 0.2.2
Summary: A python-based method for generating cosmological reionization fields
Home-page: https://github.com/plaplant/zreion
Author: Paul La Plante
Author-email: paul.laplante@unlv.edu
License: mit
Project-URL: Documentation, https://github.com/plaplant/zreion
Platform: any
Classifier: Development Status :: 4 - Beta
Classifier: Programming Language :: Python
Requires-Python: >=3.6
Provides-Extra: test
License-File: LICENSE.txt
License-File: AUTHORS.rst
